AstroInstrumentAD/dispersion_analysis.py
AstroInstrumentAD/dispersion_functions.py
AstroInstrumentAD-0.153.dist-info/LICENSE.txt
AstroInstrumentAD-0.153.dist-info/METADATA
AstroInstrumentAD-0.153.dist-info/WHEEL
AstroInstrumentAD-0.153.dist-info/top_level.txt
AstroInstrumentAD-0.153.dist-info/RECORD
