Metadata-Version: 2.1
Name: AstroInstrumentAD
Version: 0.153
Summary: A Python package to characterise the impact of atmospheric dispersion on a spectrographs throughput
Home-page: https://github.com/JamianStephan/AstroInstrumentAD
Download-URL: https://github.com/JamianStephan/AstroInstrumentAD/archive/refs/tags/v0.1.zip
Author: Jay Stephan
Author-email: Jay.Stephan@STFC.ac.uk
License: MIT
Keywords: Astronomy,Instrumentation,Atmospheric Dispersion
Classifier: Development Status :: 3 - Alpha
Classifier: Intended Audience :: Developers
Classifier: Topic :: Software Development :: Build Tools
Classifier: License :: OSI Approved :: MIT License
Classifier: Programming Language :: Python :: 3.7
License-File: LICENSE.txt
Requires-Dist: numpy
Requires-Dist: matplotlib
Requires-Dist: astropy
Requires-Dist: scipy
